twistedActor/__init__.py
twistedActor/actor.py
twistedActor/actorWrapper.py
twistedActor/baseActor.py
twistedActor/baseWrapper.py
twistedActor/command.py
twistedActor/commandQueue.py
twistedActor/device.py
twistedActor/deviceSet.py
twistedActor/deviceWrapper.py
twistedActor/dispatcherWrapper.py
twistedActor/hub.py
twistedActor/linkCommands.py
twistedActor/log.py
twistedActor/makeStartupScript.py
twistedActor/parse.py
twistedActor/scriptRunner.py
twistedActor/testUtils.py
twistedActor/version.py
sdss_twistedActor-2.0.1.dist-info/METADATA
sdss_twistedActor-2.0.1.dist-info/WHEEL
sdss_twistedActor-2.0.1.dist-info/top_level.txt
sdss_twistedActor-2.0.1.dist-info/RECORD
