Metadata-Version: 2.1
Name: sdss-twistedActor
Version: 2.0.1
Summary: Actor package based on Twisted Framework
Home-page: UNKNOWN
Author: Russell Owen
License: UNKNOWN
Platform: UNKNOWN
